{"data": {"assets/sounds/wwise2016/vo/fr_fr/characters/chogath/skins/base/chogath_base_vo_audio.wpk": {"Play_vo_Chogath_Taunt3DGeneral": [492216715], "Play_vo_Chogath_Death3D": [980633565, 1043322392, 626054668, 766868518], "Play_vo_Chogath_Joke3D": [60315382, 240297670, 846789315], "Play_vo_Chogath_Laugh3D": [571761985, 271760529, 696039951], "Play_vo_Chogath_AttackChampion2D": [681150961, 406594126, 60375609, 613929490, 77528853, 407079388, 217029348], "Play_vo_Chogath_MoveOrder2D": [581160345, 690216278, 634617880, 362502472, 113651611, 385352937, 1053150220]}}, "info": {"kind": "characters", "name": "chogath", "detail": "skin0", "type": "VO", "wad": "DATA/FINAL/Champions/Chogath.fr_FR.wad.client"}}