{"data": {"assets/sounds/wwise2016/vo/ja_jp/characters/drmundo/skins/base/drmundo_base_vo_audio.wpk": {"Play_vo_DrMundo_Taunt3DGeneral": [979746527], "Play_vo_DrMundo_Laugh3DGeneral": [477209207, 767651907, 181822648], "Play_vo_DrMundo_DrMundoBasicAttack2_cast3D": [484363952, 88542107], "Play_vo_DrMundo_DrMundoCritAttack_cast3D": [88542107, 484363952], "Play_vo_DrMundo_Joke3DGeneral": [606952823], "Play_vo_DrMundo_Death3D": [394412585, 129912823, 23380736], "Play_vo_DrMundo_MoveOrder2D": [214891619, 783517513, 343788554, 665990417, 806250177], "Play_vo_DrMundo_InfectedCleaverMissileCast_cast3D": [88542107, 484363952], "Play_vo_DrMundo_AttackChampion2D": [630409885, 579458170, 788101473, 388428975, 435403560, 264635292, 976675846]}}, "info": {"kind": "characters", "name": "drmundo", "detail": "skin0", "type": "VO", "wad": "DATA/FINAL/Champions/DrMundo.ja_JP.wad.client"}}