{"data": {"assets/sounds/wwise2016/vo/ru_ru/characters/nidalee/skins/base/nidalee_base_vo_audio.wpk": {"Play_vo_Nidalee_JavelinToss_cast3D": [290404676, 710019738, 1011178969], "Play_vo_Nidalee_NidaleeBasicAttack_cast3D": [154060301, 227704493, 769168101], "Play_vo_Nidalee_NidaleeCritAttack_cast3D": [154060301, 769168101, 290404676, 227704493], "Play_vo_Nidalee_Death3D": [283109735, 798187805, 491644254, 746777047], "Play_vo_Nidalee_AttackChampion2D": [686227381, 95706061, 772644408, 27306193, 687590009, 959694805], "Play_vo_Nidalee_Laugh3DGeneral": [311988668, 844695274, 89261041], "Play_vo_Nidalee_PrimalSurge_cast3D": [290404676, 710019738, 1011178969], "Play_vo_Nidalee_Joke3DGeneral": [978964396], "Play_vo_Nidalee_MoveOrder2D": [947039559, 862717609, 238235399, 955619534, 448534448, 394734473], "Play_vo_Nidalee_Bushwhack_cast3D": [154060301, 769168101, 290404676, 227704493], "Play_vo_Nidalee_Taunt3DGeneral": [395821046]}}, "info": {"kind": "characters", "name": "nidalee", "detail": "skin0", "type": "VO", "wad": "DATA/FINAL/Champions/Nidalee.ru_RU.wad.client"}}